pysnipeit/Classes.py
pysnipeit/__init__.py
pysnipeit/accessories.py
pysnipeit/assets.py
pysnipeit/licenses.py
pysnipeit/user.py
pysnipeit-0.0.1.dist-info/LICENSE
pysnipeit-0.0.1.dist-info/METADATA
pysnipeit-0.0.1.dist-info/WHEEL
pysnipeit-0.0.1.dist-info/top_level.txt
pysnipeit-0.0.1.dist-info/RECORD
