Metadata-Version: 2.1
Name: pysnipeit
Version: 0.0.1
Summary: an implementation of the Snipe-IT api for python
Author-email: Anthany Martin <4kmartin@gmail.com>
Classifier: Programming Language :: Python :: 3
Classifier: License :: OSI Approved :: MIT License
Classifier: Operating System :: OS Independent
Requires-Python: >=3.8
License-File: LICENSE
Requires-Dist: returns
Requires-Dist: requests
